demo/__init__.py
demo/app.py
demo/test.py
MMC_demo-0.36.dist-info/LICENSE
MMC_demo-0.36.dist-info/METADATA
MMC_demo-0.36.dist-info/WHEEL
MMC_demo-0.36.dist-info/top_level.txt
MMC_demo-0.36.dist-info/RECORD
