Metadata-Version: 2.1
Name: MMC-demo
Version: 0.36
Summary: MicroMOOC demo test
Home-page: https://micromooc.com/
Author: MicroMOOC
Author-email: support@micromooc.com
License: UNKNOWN
Platform: UNKNOWN
Classifier: Programming Language :: Python :: 3
Classifier: License :: OSI Approved :: MIT License
Classifier: Operating System :: OS Independent
